opencities/__init__.py
opencities/pages.py
opencities-0.0.4.dist-info/LICENSE
opencities-0.0.4.dist-info/METADATA
opencities-0.0.4.dist-info/WHEEL
opencities-0.0.4.dist-info/top_level.txt
opencities-0.0.4.dist-info/RECORD
