Metadata-Version: 2.1
Name: opencities
Version: 0.0.4
Summary: Packages for the OpenCities API
Home-page: https://github.com/GRInnovation/opencities
Author: Zac Thiel
Author-email: digitalservices@grcity.us
License: UNKNOWN
Platform: UNKNOWN
Classifier: Programming Language :: Python :: 3
Classifier: License :: OSI Approved :: MIT License
Classifier: Operating System :: OS Independent
Requires-Python: >=3.7.7
